.travis.yml
CHANGES.txt
README.rst
THANKS.txt
development.ini
setup.cfg
setup.py
kotti_etherpad/__init__.py
kotti_etherpad/fanstatic.py
kotti_etherpad/resources.py
kotti_etherpad/views.py
kotti_etherpad/widgets.py
kotti_etherpad.egg-info/PKG-INFO
kotti_etherpad.egg-info/SOURCES.txt
kotti_etherpad.egg-info/dependency_links.txt
kotti_etherpad.egg-info/entry_points.txt
kotti_etherpad.egg-info/not-zip-safe
kotti_etherpad.egg-info/requires.txt
kotti_etherpad.egg-info/top_level.txt
kotti_etherpad/locale/kotti_etherpad.pot
kotti_etherpad/locale/de/LC_MESSAGES/kotti_etherpad.mo
kotti_etherpad/locale/de/LC_MESSAGES/kotti_etherpad.po
kotti_etherpad/locale/en/LC_MESSAGES/kotti_etherpad.mo
kotti_etherpad/locale/en/LC_MESSAGES/kotti_etherpad.po
kotti_etherpad/locale/ja/LC_MESSAGES/kotti_etherpad.mo
kotti_etherpad/locale/ja/LC_MESSAGES/kotti_etherpad.po
kotti_etherpad/static/kotti_etherpad.css
kotti_etherpad/static/kotti_etherpad.js
kotti_etherpad/static/kotti_etherpad.min.css
kotti_etherpad/static/kotti_etherpad.min.js
kotti_etherpad/templates/etherpad-view.pt
kotti_etherpad/templates/protocol_widget.pt
kotti_etherpad/tests/__init__.py
kotti_etherpad/tests/conftest.py
kotti_etherpad/tests/test_browser.txt
kotti_etherpad/tests/test_widgets.py